<x length="1 homosexuality%1:04:00::|1.0">Homosexuality</x> in his <x length="1 opinion%1:09:00::|0.319760581844106 opinion%1:09:01::|0.1720397225022873 opinion%1:10:01::|0.17881107370261887 opinion%1:04:01::|0.1657936164637279 opinion%1:10:00::|0.16359500548725991">opinion</x> <x length="1 be%2:42:03::|0.1519361366597269 be%2:42:06::|0.1626298224070762 be%2:42:00::|0.08822167532598578 be%2:41:00::|0.11656705543852365 be%2:42:05::|0.07302217940092637 be%2:42:07::|0.10997522448098612 be%2:42:02::|0.09319243350027748 be%2:42:04::|0.10829494592135729 be%2:42:08::|0.09616052686514018">is</x> a <x length="1 deviation%1:11:00::|0.5617698168614069 deviation%1:09:00::|0.4382301831385931">deviation</x> from the <x length="1 norm%1:24:00::|0.54260222859578 norm%1:09:00::|0.45739777140422">norm</x> and <x length="1 be%2:42:03::|0.2574124382949711 be%2:42:06::|0.08573870999187844 be%2:42:00::|0.08624270119256976 be%2:41:00::|0.0922586955035897 be%2:42:05::|0.0942592784212762 be%2:42:07::|0.09381241812856354 be%2:42:02::|0.10258785130318557 be%2:42:04::|0.08823604040533042 be%2:42:08::|0.09945186675863525">is</x> <x length="1 perverse%5:00:00:negative:02|1.0">perverse</x> .
