Although S2 <x length="1 be%2:42:03::|0.23749143570541376 be%2:42:06::|0.1241119961585282 be%2:42:00::|0.0869083802853404 be%2:41:00::|0.09544000094017567 be%2:42:05::|0.08859856295134805 be%2:42:07::|0.09164389234021729 be%2:42:02::|0.09968060230182814 be%2:42:04::|0.08015373763725919 be%2:42:08::|0.09597139167988931">is</x> <x length="1 please%2:37:00::|0.49375462352724736 please%2:37:01::|0.5062453764727526">pleased</x> with the <x length="1 concession%1:10:00::|0.49049574404010376 concession%1:10:02::|0.5095042559598962">concession</x> of S1 's <x length="1 former%5:00:02:past:00|0.2921657892879833 former%3:00:00::|0.3259020283537763 former%5:00:01:past:00|0.38193218235824045">former</x> <x length="1 opinion%1:09:00::|0.34719959120809224 opinion%1:09:01::|0.16158348393740674 opinion%1:10:01::|0.16818933490827281 opinion%1:04:01::|0.15819356109535143 opinion%1:10:00::|0.16483402885087683">opinion</x> , he <x length="1 believe%2:31:00::|0.24279178059969886 believe%2:31:03::|0.18714878991486636 believe%2:31:01::|0.19399611603251868 believe%2:31:04::|0.37606331345291605">believes</x> <x length="1 jump%2:38:00::|0.14882214900215368 jump%2:30:00::|0.14602446481680495 jump%2:33:00::|0.14899674202889418 jump%2:30:01::|0.134814451636896 jump%2:38:04::|0.15869190499013058 jump%2:33:03::|0.13167216201329143 jump%2:42:00::|0.13097812551182936">jumping</x> to the <x length="1 moral%3:01:00::|0.6901773648199623 moral%3:00:00::|0.3098226351800377">moral</x> <x length="1 high%3:00:02::|0.30692699298507675 high%5:00:00:superior:01|0.19109791042803873 high%3:00:01::|0.17823936473220733 high%3:00:03::|0.15295496121111873 high%5:00:00:elated:00|0.17078077064355845">high</x> <x length="1 ground%1:16:00::|0.23816931086654217 ground%1:27:00::|0.18960850477249588 ground%1:17:00::|0.2223684046131415 ground%1:24:00::|0.1848390898662037 ground%1:09:00::|0.1650146898816166">ground</x> <x length="1 still%4:02:01::|0.3644044651526267 still%4:02:04::|0.21699367016934235 still%4:02:00::|0.21584216106629434 still%4:02:02::|0.20275970361173662">still</x> <x length="1 ignore%2:32:02::|0.28605402046111317 ignore%2:31:03::|0.21767765969535627 ignore%2:32:00::|0.2633021805514916 ignore%2:39:00::|0.23296613929203905">ignores</x> <x length="1 other%3:00:00::|0.584903934901431 other%5:00:00:past:00|0.22040420026133273 other%5:00:00:added:00|0.19469186483723627">other</x> <x length="1 issue%1:09:01::|0.47756925953051976 issue%1:04:01::|0.17480907355962094 issue%1:10:00::|0.1599314094390835 issue%1:09:00::|0.18769025747077586">issues</x> .
