S1 <x length="1 hold%2:36:00::|0.039592837877258306 hold%2:40:00::|0.04953259456074232 hold%2:35:03::|0.04299349724708697 hold%2:42:00::|0.06659128672750228 hold%2:35:00::|0.047692847648998386 hold%2:37:00::|0.05900321338898131 hold%2:35:01::|0.036103998557600187 hold%2:31:01::|0.04588609859788265 hold%2:42:13::|0.04090380915702271 hold%2:40:04::|0.038321723345484816 hold%2:42:01::|0.0435750735093583 hold%2:35:02::|0.044558710627181856 hold%2:42:05::|0.03873843264830294 hold%2:40:02::|0.03898044549344996 hold%2:31:04::|0.040311916332423224 hold%2:40:03::|0.04159245679294829 hold%2:41:00::|0.04121582308752739 hold%2:32:13::|0.04063434631347897 hold%2:31:08::|0.04020562005568255 hold%2:31:10::|0.04099971677888264 hold%2:42:14::|0.04034829704257086 hold%2:42:07::|0.04042101821172982 hold%2:42:02::|0.04179623599790346">holds</x> <x length="1 hope%1:12:01::|0.4005826054016203 hope%1:09:00::|0.21647026970536656 hope%1:12:00::|0.19482728032991017 hope%1:18:00::|0.18811984456310302">hope</x> that <x length="1 gay%5:00:00:homosexual:00|0.16052304591994665 gay%5:00:00:cheerful:00|0.17443485515925308 gay%5:00:00:indulgent:00|0.16759082147528287 gay%5:00:00:joyous:00|0.16155154906213295 gay%5:00:02:joyous:00|0.1648496271323563 gay%5:00:00:colorful:03|0.1710501012510281">gay</x> <x length="1 marriage%1:26:00::|0.4527989956645801 marriage%1:04:00::|0.2915598920326168 marriage%1:14:00::|0.255641112302803">marriage</x> <x length="1 will%2:42:00::|0.27199700497243806 will%2:32:00::|0.23928172294471015 will%2:31:01::|0.24238845360131336 will%2:31:00::|0.2463328184815385">will</x> <x length="1 be%2:42:03::|0.15829996854062586 be%2:42:06::|0.20485649401373027 be%2:42:00::|0.09976829239099864 be%2:41:00::|0.0943784625799805 be%2:42:05::|0.07971567494420703 be%2:42:07::|0.08765332510179064 be%2:42:02::|0.09525908641635247 be%2:42:04::|0.08198391305776838 be%2:42:08::|0.09808478295454624">be</x> <x length="1 ban%2:32:00::|0.5139718318195106 ban%2:41:00::|0.48602816818048944">banned</x> <x length="1 everywhere%4:02:00::|1.0">everywhere</x> .
