S1 <x length="1 cite%2:32:00::|0.2894538383554259 cite%2:32:01::|0.2253322567166333 cite%2:36:00::|0.22404918900916554 cite%2:32:02::|0.2611647159187754">cites</x> <x length="1 several%5:00:00:some:00|0.5322250819429777 several%5:00:00:different:00|0.232853888847242 several%5:00:00:individual:00|0.2349210292097802">several</x> <x length="1 culture%1:14:00::|0.27714847499141093 culture%1:09:01::|0.2353496474868472 culture%1:09:00::|0.24737646107598776 culture%1:04:01::|0.24012541644575416">cultures</x> who <x length="1 practice%1:04:04::|0.1506538457758093 practice%1:04:00::|0.285287138973791 practice%1:04:03::|0.17201024096883383 practice%1:09:00::|0.17885064231624495 practice%1:04:02::|0.21319813196532097">practices</x> <x length="1 gay%5:00:00:homosexual:00|0.16290750585667207 gay%5:00:00:cheerful:00|0.1754902329659408 gay%5:00:00:indulgent:00|0.16195912482761943 gay%5:00:00:joyous:00|0.15868534057978328 gay%5:00:02:joyous:00|0.1727144762298078 gay%5:00:00:colorful:03|0.16824331954017677">gay</x> <x length="1 union%1:14:01::|0.43282163896440606 union%1:04:02::|0.2828805019094269 union%1:15:00::|0.284297859126167">unions</x> <x length="1 such%5:00:01:specified:00|0.5369790753840432 such%5:00:00:much:00|0.2351410808889979 such%5:00:00:specified:00|0.22787984372695888">such</x> as <x length="1 roman%1:18:00::|1.0">Romans</x> and <x length="1 celt%1:18:00::|1.0">Celts</x> .
