<x length="1 redefine%2:42:00::|1.0">Redefining</x> <x length="1 marriage%1:26:00::|0.4821315293848317 marriage%1:04:00::|0.2938669233360446 marriage%1:14:00::|0.22400154727912366">marriage</x> to <x length="1 include%2:31:00::|0.2163808302708844 include%2:41:03::|0.2111103539063279 include%2:42:00::|0.35694859865672585 include%2:30:00::|0.21556021716606183">include</x> <x length="1 same%3:00:04::|0.2162914344806333 same%3:00:02::|0.31584612337696727 same%3:00:00::|0.2507009293357848 same%5:00:00:unchanged:00|0.2171615128066148">same-sex</x> <x length="1 couple%1:14:01::|0.35529783880365107 couple%1:23:01::|0.19815705995771005 couple%1:14:00::|0.2523843893654153 couple%1:23:00::|0.19416071187322356">couples</x> <x length="1 upset%2:37:01::|0.32711298785875526 upset%2:30:00::|0.347653381004148 upset%2:37:00::|0.32523363113709675">upsets</x> the <x length="1 sensitivity%1:09:00::|0.3505363690739409 sensitivity%1:07:00::|0.33829683699835683 sensitivity%1:12:00::|0.31116679392770225">sensitivities</x> of these <x length="1 people%1:14:00::|0.46030922493631155 people%1:14:01::|0.18836683407421154 people%1:14:03::|0.17153606551288822 people%1:14:02::|0.1797878754765887">people</x> .
