<x length="1 roommate%1:18:00::|1.0">Roommates</x> <x length="1 be%2:42:03::|0.2726204098643608 be%2:42:06::|0.062247885996189384 be%2:42:00::|0.09631495547883565 be%2:41:00::|0.10149833745716144 be%2:42:05::|0.11250245939658815 be%2:42:07::|0.08340978865238002 be%2:42:02::|0.09361961762402755 be%2:42:04::|0.07930518388114084 be%2:42:08::|0.09848136164931634">are</x> <x length="1 single%3:00:00::|1.0">single</x> and <x length="1 should%2:42:02::|0.48758425215410756 should%2:42:01::|0.5124157478458924">should</x> <x length="1 not%4:02:00::|1.0">not</x> <x length="1 have%2:40:04::|0.05836920386392713 have%2:30:00::|0.042678710146878844 have%2:40:00::|0.07379216796434426 have%2:39:06::|0.05125104644580528 have%2:40:01::|0.04233073145782469 have%2:42:05::|0.04356612191840952 have%2:36:00::|0.04442270653837727 have%2:42:00::|0.05375613437476478 have%2:40:02::|0.045708060356289354 have%2:29:02::|0.047087212070157834 have%2:34:00::|0.054679972521026944 have%2:41:00::|0.035559766324015654 have%2:29:05::|0.044787790346683246 have%2:30:01::|0.039328536435996694 have%2:42:12::|0.04855926496874269 have%2:32:00::|0.04406533914377112 have%2:40:03::|0.04616571289852595 have%2:40:05::|0.046416600569372676 have%2:42:08::|0.044690771304825835 have%2:29:00::|0.04534172204973296 have%2:35:00::|0.047442428300527174">have</x> <x length="1 marriage%1:26:00::|0.4569166899235014 marriage%1:04:00::|0.29373980072523775 marriage%1:14:00::|0.2493435093512608">marriage</x> <x length="1 benefit%1:21:00::|0.3883038469003431 benefit%1:07:00::|0.37311431157745706 benefit%1:10:00::|0.23858184152219994">benefits</x> .
