S1 <x length="1 threaten%2:32:00::|0.40544155180652597 threaten%2:32:01::|0.34439849353738317 threaten%2:42:00::|0.2501599546560909">threatens</x> to <x length="1 respond%2:31:00::|0.4265623604061833 respond%2:32:00::|0.3047599045119814 respond%2:31:01::|0.26867773508183523">respond</x> with <x length="1 similar%3:00:00::|0.7354349235875599 similar%3:00:04::|0.2645650764124401">similar</x> <x length="1 action%1:04:01::|0.09451269578801644 action%1:04:02::|0.23972541039720888 action%1:04:03::|0.14875152934645652 action%1:22:00::|0.1049232787949554 action%1:26:00::|0.10727885779592769 action%1:07:00::|0.10418575375972275 action%1:10:00::|0.09845812765530755 action%1:06:00::|0.1021643464624049">actions</x> against the <x length="1 church%1:06:00::|0.41227753059688027 church%1:14:00::|0.3985593012778856 church%1:04:00::|0.18916316812523412">church</x> , like <x length="1 protest%2:32:00::|0.525527128275122 protest%2:41:00::|0.47447287172487795">protesting</x> <x length="1 ceremonial%5:00:00:formal:01|1.0">ceremonial</x> <x length="1 event%1:26:00::|0.3551301195792759 event%1:03:00::|0.644869880420724">events</x> and <x length="1 church%1:06:00::|0.34972674533759346 church%1:14:00::|0.392939051684705 church%1:04:00::|0.25733420297770154">church</x> <x length="1 services%1:04:00::|1.0">services</x> .
