S1 and S2 <x length="1 be%2:42:03::|0.12886090028396058 be%2:42:06::|0.1517231227209374 be%2:42:00::|0.09010480339832515 be%2:41:00::|0.1025488761542873 be%2:42:05::|0.11946965516629297 be%2:42:07::|0.10769166652954669 be%2:42:02::|0.10184792599179655 be%2:42:04::|0.098869240297542 be%2:42:08::|0.09888380945731122">are</x> <x length="1 talk%2:32:01::|0.39133194778199476 talk%2:32:00::|0.12035889490908852 talk%2:32:06::|0.18458806804423372 talk%2:32:02::|0.1518150500979429 talk%2:32:03::|0.15190603916674006">talking</x> about the <x length="1 view%1:09:02::|0.20529274034096118 view%1:09:00::|0.11153204617734153 view%1:15:00::|0.10552223999125676 view%1:09:01::|0.1183350478319431 view%1:09:04::|0.10929849882834353 view%1:04:00::|0.11933992380483592 view%1:06:00::|0.11249913112371196 view%1:10:00::|0.11818037190160599">views</x> of <x length="1 gay%5:00:00:homosexual:00|0.15722022844155478 gay%5:00:00:cheerful:00|0.179326886224317 gay%5:00:00:indulgent:00|0.17067662258368188 gay%5:00:00:joyous:00|0.1578721889050039 gay%5:00:02:joyous:00|0.16821084796100128 gay%5:00:00:colorful:03|0.1666932258844412">gay</x> <x length="1 marriage%1:26:00::|0.41069541670212895 marriage%1:04:00::|0.3192690162137955 marriage%1:14:00::|0.27003556708407567">marriage</x> in our <x length="1 culture%1:14:00::|0.25804563768629557 culture%1:09:01::|0.23366323946545925 culture%1:09:00::|0.3039845087808106 culture%1:04:01::|0.20430661406743472">culture</x> .
