S2 <x length="1 believe%2:31:00::|0.20950604782236945 believe%2:31:03::|0.1634548398314436 believe%2:31:01::|0.2008077103611498 believe%2:31:04::|0.42623140198503706">believes</x> they <x length="1 be%2:42:03::|0.1588621069379813 be%2:42:06::|0.1134824587421429 be%2:42:00::|0.08936163020523755 be%2:41:00::|0.10193966796973601 be%2:42:05::|0.14605196628749892 be%2:42:07::|0.0965509955101948 be%2:42:02::|0.10296187369860431 be%2:42:04::|0.08708014139386386 be%2:42:08::|0.10370915925474043">are</x> <x length="1 nothing%1:23:00::|1.0">nothing</x> <x length="1 alike%4:02:00::|1.0">alike</x> while S1 <x length="1 believe%2:31:00::|0.1951040461113521 believe%2:31:03::|0.2003139918340626 believe%2:31:01::|0.1976923986913759 believe%2:31:04::|0.4068895633632094">believes</x> they <x length="1 have%2:40:04::|0.0543496706272463 have%2:30:00::|0.03365954060296098 have%2:40:00::|0.08004763896907886 have%2:39:06::|0.0499760565780703 have%2:40:01::|0.04272770657902548 have%2:42:05::|0.04797268876698672 have%2:36:00::|0.040677744189698696 have%2:42:00::|0.05295731810191601 have%2:40:02::|0.04591558290130629 have%2:29:02::|0.04710828106019274 have%2:34:00::|0.0461264305747536 have%2:41:00::|0.050472138221020646 have%2:29:05::|0.04900284573351145 have%2:30:01::|0.041375930084028435 have%2:42:12::|0.042976075691843016 have%2:32:00::|0.04252291266724824 have%2:40:03::|0.04607543461273662 have%2:40:05::|0.04398941694627376 have%2:42:08::|0.047412001318259143 have%2:29:00::|0.04606231970060817 have%2:35:00::|0.04859226607323464">have</x> <x length="1 many%3:00:00::|1.0">many</x> <x length="1 similarity%1:07:00::|1.0">similarities</x> .
