S1 <x length="1 be%2:42:03::|0.2543536874263012 be%2:42:06::|0.06637207946253806 be%2:42:00::|0.09810226036380912 be%2:41:00::|0.10013928767654864 be%2:42:05::|0.10654601335403607 be%2:42:07::|0.07917436335728434 be%2:42:02::|0.09836121276550604 be%2:42:04::|0.09919161950683268 be%2:42:08::|0.09775947608714375">is</x> against <x length="1 gay%5:00:00:homosexual:00|0.15601043863637182 gay%5:00:00:cheerful:00|0.18044094695759025 gay%5:00:00:indulgent:00|0.1589830893793544 gay%5:00:00:joyous:00|0.1575080815604368 gay%5:00:02:joyous:00|0.17311164006989727 gay%5:00:00:colorful:03|0.17394580339634944">gay</x> <x length="1 right%1:07:00::|0.21540379199298107 right%1:15:00::|0.13625201533552297 right%1:08:00::|0.1316411260597526 right%1:07:01::|0.13178076437287486 right%1:14:00::|0.13096896490112941 right%1:06:00::|0.12615962156747898 right%1:04:00::|0.1277937157702602">rights</x> and <x length="1 believe%2:31:00::|0.2258985112316021 believe%2:31:03::|0.16945742644738152 believe%2:31:01::|0.19669749281036727 believe%2:31:04::|0.4079465695106491">believes</x> they <x length="1 earn%2:40:03::|0.48078067029554766 earn%2:40:01::|0.5192193297044523">earned</x> their <x length="1 freedom%1:26:00::|0.7151234029313601 freedom%1:26:01::|0.2848765970686399">freedom</x> of <x length="1 speech%1:10:01::|0.2631439135580991 speech%1:10:00::|0.27148600402287043 speech%1:10:05::|0.23388557398851353 speech%1:10:03::|0.2314845084305168">speech</x> through <x length="1 serve%2:33:00::|0.13191378681511318 serve%2:35:00::|0.08425493531384441 serve%2:42:03::|0.07065733668678012 serve%2:41:02::|0.09893879595727419 serve%2:34:01::|0.07987711171155439 serve%2:42:00::|0.08202423982908044 serve%2:41:00::|0.09915986170876191 serve%2:42:01::|0.08807662399573961 serve%2:42:02::|0.07798284166949646 serve%2:34:00::|0.1043902422131754 serve%2:41:01::|0.08272422409917997">serving</x> in the <x length="1 military%3:00:02::|0.27930412132091437 military%3:00:01::|0.41453838664133885 military%3:01:00::|0.3061574920377468">military</x> .
