He <x length="1 believe%2:31:00::|0.28958519661096116 believe%2:31:03::|0.12493849407853042 believe%2:31:01::|0.19015093596677965 believe%2:31:04::|0.39532537334372875">believes</x> <x length="1 radical%5:00:00:immoderate:00|0.5123242943030224 radical%5:00:00:new:00|0.4876757056969776">radical</x> <x length="1 leftist%1:18:00::|1.0">leftists</x> <x length="1 create%2:36:02::|0.2669144134332406 create%2:36:00::|0.49675734537917515 create%2:36:01::|0.23632824118758425">created</x> the <x length="1 group%1:03:00::|0.6909353881273457 group%1:27:00::|0.3090646118726543">group</x> as a <x length="1 way%1:07:01::|0.13779510392722422 way%1:06:00::|0.07898040428619114 way%1:23:00::|0.0858956776420143 way%1:04:01::|0.1684384512730864 way%1:04:02::|0.1050182835931939 way%1:15:00::|0.08980677486799678 way%1:04:00::|0.0833037169084946 way%1:26:00::|0.0789450040768034 way%1:07:02::|0.08570017772532071 way%1:09:00::|0.0861164056996746">way</x> of <x length="1 promote%2:41:01::|0.4201195276866303 promote%2:32:00::|0.2960764741760601 promote%2:41:00::|0.28380399813730967">promoting</x> <x length="1 fear%1:12:00::|0.6845030211504268 fear%1:12:01::|0.3154969788495732">fear</x> of <x length="1 christian%1:18:00::|1.0">Christians</x> .
