<x length="1 accord%2:42:00::|0.6133791028573135 accord%2:40:00::|0.38662089714268655">According</x> to his <x length="1 democrat%1:18:00::|0.4835835269882865 democrat%1:18:01::|0.5164164730117136">democrats</x> <x length="1 want%2:35:00::|0.1943064662439005 want%2:37:00::|0.4796256471080017 want%2:34:00::|0.18321205386648468 want%2:31:01::|0.14285583278161323">want</x> to <x length="1 do%2:41:04::|0.1007126062644312 do%2:41:01::|0.16142428318764468 do%2:36:01::|0.060837810393716336 do%2:42:01::|0.061729757605339816 do%2:41:03::|0.06694958255577489 do%2:41:02::|0.07355969026748996 do%2:29:09::|0.0671175546198685 do%2:36:02::|0.07114757379869395 do%2:42:00::|0.06517670681633332 do%2:36:00::|0.06731676704805814 do%2:38:00::|0.06548148333066979 do%2:29:04::|0.0696697007066733 do%2:42:02::|0.06887648340530607">do</x> the <x length="1 right%3:00:00::|0.14468029890593523 right%3:00:02::|0.32056606606713023 right%5:00:00:appropriate:00|0.1326330925762157 right%3:00:04::|0.12498034970968444 right%5:00:01:proper:00|0.13857403588156955 right%3:00:01::|0.1385661568594649">right</x> <x length="1 thing%1:06:00::|0.08676812847339274 thing%1:11:00::|0.09618989329705938 thing%1:04:00::|0.13724165643084038 thing%1:10:00::|0.11043627341841024 thing%1:26:00::|0.11716419490494508 thing%1:09:02::|0.09754409308767743 thing%1:09:01::|0.07930179758530759 thing%1:09:00::|0.09544436220477143 thing%1:06:01::|0.09268082848908973 thing%1:07:00::|0.08722877210850598">thing</x> <x length="1 however%4:02:00::|0.3303320655004387 however%4:02:02::|0.21065375914983928 however%4:02:04::|0.249260823802823 however%4:02:01::|0.2097533515468991">however</x> , they <x length="1 be%2:42:03::|0.19187160697570618 be%2:42:06::|0.09083290877882452 be%2:42:00::|0.0951378095969673 be%2:41:00::|0.09551506853714015 be%2:42:05::|0.15124508722227128 be%2:42:07::|0.09268239106095034 be%2:42:02::|0.10404089427144378 be%2:42:04::|0.081041817605435 be%2:42:08::|0.09763241595126138">are</x> <x length="1 force%1:07:00::|0.13382655046601133 force%1:14:00::|0.13338104893780442 force%1:07:01::|0.16558751504144825 force%1:14:01::|0.1319664210340424 force%1:04:01::|0.1725041043302274 force%1:18:00::|0.1380384453408562 force%1:19:00::|0.12469591484961">force</x> to <x length="1 moderate%2:32:00::|1.0">moderate</x> their <x length="1 opinion%1:09:00::|0.3048428605684342 opinion%1:09:01::|0.22422004128296874 opinion%1:10:01::|0.152508186818504 opinion%1:04:01::|0.1628392800014186 opinion%1:10:00::|0.15558963132867437">opinions</x> for <x length="1 public%5:00:00:common:02|0.47856469900758536 public%3:00:00::|0.5214353009924146">public</x> <x length="1 approval%1:04:02::|0.4067157505845981 approval%1:26:00::|0.264607274310076 approval%1:12:00::|0.3286769751053259">approval</x> .
