S1 <x length="1 explain%2:32:01::|0.20642966679720165 explain%2:32:00::|0.5335774103066283 explain%2:32:02::|0.25999292289617">explains</x> that <x length="1 love%1:09:00::|0.18601628797105507 love%1:12:00::|0.38359524134513606 love%1:12:01::|0.23014657283937495 love%1:18:00::|0.20024189784443394">love</x> <x length="1 be%2:42:03::|0.22593413641036503 be%2:42:06::|0.10786259447059737 be%2:42:00::|0.08743333084475266 be%2:41:00::|0.09847425183765804 be%2:42:05::|0.12203549666105842 be%2:42:07::|0.09299106531255034 be%2:42:02::|0.09014735311542431 be%2:42:04::|0.07707875492130911 be%2:42:08::|0.09804301642628482">is</x> <x length="1 present%3:00:01::|0.3152685343953734 present%3:00:02::|0.6847314656046266">present</x> in all <x length="1 marriage%1:26:00::|0.4819479076728988 marriage%1:04:00::|0.2769180086812307 marriage%1:14:00::|0.24113408364587058">marriage</x> so the <x length="1 claim%1:10:02::|0.2393397430080417 claim%1:04:00::|0.21657866477124568 claim%1:10:00::|0.22390238612962937 claim%1:07:02::|0.157151624480586 claim%1:07:01::|0.16302758161049724">claims</x> <x length="1 make%2:30:00::|0.05109304250059899 make%2:42:00::|0.030789739171008915 make%2:41:00::|0.06336704884454003 make%2:36:01::|0.03774003332459901 make%2:36:12::|0.03660082569132627 make%2:31:00::|0.035352287260808295 make%2:36:05::|0.0338784278519708 make%2:31:13::|0.0359315758254406 make%2:36:13::|0.03227218631642152 make%2:41:03::|0.033692218431010904 make%2:38:02::|0.03427541150011804 make%2:38:00::|0.030597037095516595 make%2:36:08::|0.02951615392979203 make%2:32:00::|0.02614529641105046 make%2:36:15::|0.032496098064532346 make%2:36:09::|0.031035812374288794 make%2:40:01::|0.03407448521303282 make%2:30:15::|0.034129439366124295 make%2:42:05::|0.034129699731513356 make%2:41:13::|0.03385382472183455 make%2:36:11::|0.03325838045972732 make%2:36:00::|0.04898475353187769 make%2:40:02::|0.032990906277996106 make%2:36:04::|0.03714940672871959 make%2:29:08::|0.03351082877114106 make%2:38:05::|0.03371273899958747 make%2:29:00::|0.03471349329384206 make%2:30:02::|0.0347088483115801">made</x> by S2 about <x length="1 gay%5:00:00:homosexual:00|0.1601464605255473 gay%5:00:00:cheerful:00|0.18195646145342906 gay%5:00:00:indulgent:00|0.17342222981969613 gay%5:00:00:joyous:00|0.15840611502834406 gay%5:00:02:joyous:00|0.16249223193494014 gay%5:00:00:colorful:03|0.16357650123804335">gay</x> <x length="1 marriage%1:26:00::|0.5897650969424119 marriage%1:04:00::|0.18667007593230905 marriage%1:14:00::|0.22356482712527903">marriage</x> <x length="1 lead%2:38:00::|0.07192698609080697 lead%2:42:12::|0.08139587871691718 lead%2:38:01::|0.08330527245840029 lead%2:41:00::|0.061964246946532034 lead%2:41:12::|0.07382998935686563 lead%2:42:03::|0.06863665414667255 lead%2:42:01::|0.07001472898552337 lead%2:42:08::|0.055616873499307766 lead%2:42:00::|0.07061233460368926 lead%2:32:00::|0.07891093092905839 lead%2:36:00::|0.05551973796048542 lead%2:42:02::|0.06220696221287252 lead%2:42:04::|0.10329757504750428 lead%2:38:02::|0.06276182904536425">leading</x> to <x length="1 incest%1:04:00::|1.0">incest</x> , <x length="1 could%2:42:00::|1.0">could</x> <x length="1 be%2:42:03::|0.23135517767631586 be%2:42:06::|0.16386990373572236 be%2:42:00::|0.0695511096577826 be%2:41:00::|0.09588132838384096 be%2:42:05::|0.06372874051401531 be%2:42:07::|0.08770762852941306 be%2:42:02::|0.09065250605374661 be%2:42:04::|0.09716221204185788 be%2:42:08::|0.1000913934073054">be</x> <x length="1 use%2:34:01::|0.5706586765985627 use%2:34:02::|0.2010674252718153 use%2:34:00::|0.22827389812962195">used</x> for <x length="1 straight%3:00:01::|0.2818159418232523 straight%5:00:00:continuous:01|0.26244895952849095 straight%3:00:03::|0.24403523383260067 straight%5:00:00:erect:00|0.21169986481565606">straight</x> <x length="1 marriage%1:26:00::|0.5932620816433516 marriage%1:04:00::|0.19005316061136368 marriage%1:14:00::|0.21668475774528478">marriage</x> <x length="1 as%4:02:00::|1.0">as</x> <x length="1 well%4:02:00::|0.24842981091531405 well%4:02:05::|0.1376477935336427 well%4:02:08::|0.12408987246696268 well%4:02:03::|0.12373805705469204 well%4:02:07::|0.115776783369863 well%4:02:15::|0.13026273246578654 well%4:02:11::|0.12005495019373907">well</x> .
