He <x length="1 think%2:31:01::|0.27352161937664904 think%2:31:00::|0.15004805502612986 think%2:31:03::|0.10466755543915586 think%2:31:02::|0.11745383440591609 think%2:31:06::|0.11224725775791361 think%2:36:00::|0.11791039547762679 think%2:31:09::|0.12415128251660874">thinks</x> <x length="1 family%1:14:02::|0.21125504333502357 family%1:14:03::|0.13413141284557836 family%1:14:01::|0.1309586461209109 family%1:14:00::|0.24499617599305037 family%1:18:00::|0.14002068024873543 family%1:14:04::|0.13863804145670128">family</x> <x length="1 be%2:42:03::|0.17398031906422878 be%2:42:06::|0.1605281098543632 be%2:42:00::|0.08751503833956963 be%2:41:00::|0.10671730129887076 be%2:42:05::|0.13218119877754614 be%2:42:07::|0.08810784312103663 be%2:42:02::|0.08079881036276794 be%2:42:04::|0.07398353408968507 be%2:42:08::|0.09618784509193201">is</x> a <x length="1 basic%3:00:00::|0.48479969199681755 basic%5:00:00:essential:00|0.2497465063232207 basic%5:00:00:standard:01|0.2654538016799617">basic</x> <x length="1 unit%1:24:00::|0.28352862728047634 unit%1:14:00::|0.18505354755095635 unit%1:23:00::|0.1678525483202648 unit%1:17:00::|0.18687409896267826 unit%1:09:00::|0.17669117788562425">unit</x> <x length="1 traditionally%4:02:00::|1.0">traditionally</x> <x length="1 consist%2:42:00::|1.0">consisting</x> of two <x length="1 parent%1:18:00::|1.0">parents</x> <x length="1 raise%2:40:00::|0.06580572491183515 raise%2:38:00::|0.05240826631733346 raise%2:30:02::|0.07778580558694376 raise%2:30:01::|0.09395961948337868 raise%2:41:00::|0.17292230459039057 raise%2:36:01::|0.08110755591422789 raise%2:32:00::|0.07364965582639767 raise%2:36:03::|0.06912136738258862 raise%2:30:00::|0.0727416022234424 raise%2:36:02::|0.07091111684894848 raise%2:38:02::|0.09182571005738607 raise%2:37:08::|0.07776127085712733">raising</x> <x length="1 child%1:18:01::|0.5860194204355026 child%1:18:00::|0.4139805795644974">children</x> .
