S1 <x length="1 refute%2:32:00::|0.5042742630573033 refute%2:31:00::|0.4957257369426967">refutes</x> this <x length="1 assertion%1:10:00::|0.5020903484085464 assertion%1:10:01::|0.4979096515914536">assertion</x> , <x length="1 cite%2:32:00::|0.2506760139419493 cite%2:32:01::|0.2491717418042845 cite%2:36:00::|0.24024685932069428 cite%2:32:02::|0.25990538493307186">citing</x> a <x length="1 number%1:07:00::|0.29622939750510835 number%1:10:03::|0.11532335509568864 number%1:10:02::|0.11493401861644677 number%1:10:01::|0.13202394268884768 number%1:23:00::|0.10533990394943914 number%1:10:00::|0.12227773969278308 number%1:10:04::|0.11387164245168645">number</x> of <x length="1 country%1:15:00::|0.2832621691366059 country%1:14:01::|0.1635287680337703 country%1:15:01::|0.2044574289811668 country%1:14:00::|0.1791512689340599 country%1:15:02::|0.16960036491439706">countries</x> which <x length="1 recognize%2:41:00::|0.13002274186373897 recognize%2:31:02::|0.19383115057461447 recognize%2:31:01::|0.13897410747679473 recognize%2:31:00::|0.12062850610661947 recognize%2:32:00::|0.12058896328874215 recognize%2:39:01::|0.16185388122437147 recognize%2:32:01::|0.13410064946511885">recognize</x> <x length="1 same%3:00:04::|0.22662467811459783 same%3:00:02::|0.27759116562256697 same%3:00:00::|0.2919660004015695 same%5:00:00:unchanged:00|0.2038181558612659">same-sex</x> <x length="1 marriage%1:26:00::|0.5046793169226544 marriage%1:04:00::|0.2592216900232625 marriage%1:14:00::|0.2360989930540831">marriage</x> and <x length="1 compare%2:31:00::|0.41289325483561 compare%2:42:00::|0.2941383363695063 compare%2:31:01::|0.2929684087948836">compares</x> the <x length="1 lack%1:26:00::|1.0">lack</x> of <x length="1 reproductive%5:00:00:fruitful:00|1.0">reproductive</x> <x length="1 potential%3:00:00::|0.6218157637758044 potential%5:00:00:prospective:00|0.3781842362241956">potential</x> for <x length="1 homosexual%3:00:00::|1.0">homosexual</x> <x length="1 couple%1:14:01::|0.45841857687326526 couple%1:23:01::|0.15317595766941486 couple%1:14:00::|0.20965422385086124 couple%1:23:00::|0.1787512416064587">couples</x> to a <x length="1 heterosexual%3:00:00::|1.0">heterosexual</x> <x length="1 couple%1:14:01::|0.44335268576190445 couple%1:23:01::|0.19826112914385433 couple%1:14:00::|0.16739690876770794 couple%1:23:00::|0.1909892763265334">couple</x> that <x length="1 choose%2:31:00::|0.2763480485390468 choose%2:31:02::|0.38111511885873517 choose%2:31:01::|0.3425368326022181">chooses</x> <x length="1 not%4:02:00::|1.0">not</x> to <x length="1 have%2:40:04::|0.05202015180114342 have%2:30:00::|0.05179286995369631 have%2:40:00::|0.08706041107621185 have%2:39:06::|0.03811056732068906 have%2:40:01::|0.04408732423300156 have%2:42:05::|0.044808114517834785 have%2:36:00::|0.04902434101512157 have%2:42:00::|0.03919734014652743 have%2:40:02::|0.0454394294926103 have%2:29:02::|0.04733926743432872 have%2:34:00::|0.04890886675803844 have%2:41:00::|0.05020313800806765 have%2:29:05::|0.044721848275539745 have%2:30:01::|0.04580937900976626 have%2:42:12::|0.0395424401402908 have%2:32:00::|0.04471528750433558 have%2:40:03::|0.047005251689587045 have%2:40:05::|0.04494241673616811 have%2:42:08::|0.04498109215737568 have%2:29:00::|0.04431617685625063 have%2:35:00::|0.045974285873415004">have</x> <x length="1 child%1:18:01::|0.6142662984719259 child%1:18:00::|0.38573370152807407">children</x> or <x length="1 be%2:42:03::|0.2489674392730518 be%2:42:06::|0.09355246044104999 be%2:42:00::|0.09359878136801078 be%2:41:00::|0.09773299496435246 be%2:42:05::|0.07759347272655857 be%2:42:07::|0.08466560309789398 be%2:42:02::|0.10317528326527219 be%2:42:04::|0.1010757756420516 be%2:42:08::|0.09963818922175877">is</x> <x length="1 unable%3:00:00::|0.6594989219144703 unable%5:00:00:incapable:00|0.34050107808552965">unable</x> to <x length="1 have%2:40:04::|0.05613438481623034 have%2:30:00::|0.04823734699451798 have%2:40:00::|0.09521153159455421 have%2:39:06::|0.044181782550955395 have%2:40:01::|0.04498880822028597 have%2:42:05::|0.04588310084027581 have%2:36:00::|0.04370106349155683 have%2:42:00::|0.03979739322658314 have%2:40:02::|0.04453903408973181 have%2:29:02::|0.04418275066061022 have%2:34:00::|0.048152177693614136 have%2:41:00::|0.05128751967584836 have%2:29:05::|0.044229268223764946 have%2:30:01::|0.04508221337465367 have%2:42:12::|0.040006775543805814 have%2:32:00::|0.041642376661126856 have%2:40:03::|0.04519050303677505 have%2:40:05::|0.04385722435141764 have%2:42:08::|0.04445949413011607 have%2:29:00::|0.043968046951587035 have%2:35:00::|0.045267203871988716">have</x> <x length="1 child%1:18:01::|0.6953324867867638 child%1:18:00::|0.30466751321323615">children</x> .
